nasa_api_package/__init__.py
nasa_api_package-0.1.0.dist-info/WHEEL
nasa_api_package-0.1.0.dist-info/METADATA
nasa_api_package-0.1.0.dist-info/RECORD
